azure/mgmt/servicenetworking/__init__.py
azure/mgmt/servicenetworking/_client.py
azure/mgmt/servicenetworking/_configuration.py
azure/mgmt/servicenetworking/_model_base.py
azure/mgmt/servicenetworking/_patch.py
azure/mgmt/servicenetworking/_serialization.py
azure/mgmt/servicenetworking/_validation.py
azure/mgmt/servicenetworking/_version.py
azure/mgmt/servicenetworking/py.typed
azure/mgmt/servicenetworking/aio/__init__.py
azure/mgmt/servicenetworking/aio/_client.py
azure/mgmt/servicenetworking/aio/_configuration.py
azure/mgmt/servicenetworking/aio/_patch.py
azure/mgmt/servicenetworking/aio/operations/__init__.py
azure/mgmt/servicenetworking/aio/operations/_operations.py
azure/mgmt/servicenetworking/aio/operations/_patch.py
azure/mgmt/servicenetworking/models/__init__.py
azure/mgmt/servicenetworking/models/_enums.py
azure/mgmt/servicenetworking/models/_models.py
azure/mgmt/servicenetworking/models/_patch.py
azure/mgmt/servicenetworking/operations/__init__.py
azure/mgmt/servicenetworking/operations/_operations.py
azure/mgmt/servicenetworking/operations/_patch.py
azure_mgmt_servicenetworking-2.0.0.dist-info/LICENSE
azure_mgmt_servicenetworking-2.0.0.dist-info/METADATA
azure_mgmt_servicenetworking-2.0.0.dist-info/WHEEL
azure_mgmt_servicenetworking-2.0.0.dist-info/top_level.txt
azure_mgmt_servicenetworking-2.0.0.dist-info/RECORD
